aitelegrambot/__init__.py
aitelegrambot/__main__.py
aitelegrambot/bot.py
aitelegrambot/commandhandlers.py
aitelegrambot/constants.py
aitelegrambot-0.8.4.dist-info/METADATA
aitelegrambot-0.8.4.dist-info/WHEEL
aitelegrambot-0.8.4.dist-info/entry_points.txt
aitelegrambot-0.8.4.dist-info/licenses/LICENSE.md
aitelegrambot-0.8.4.dist-info/RECORD
