Metadata-Version: 2.3
Name: aitelegrambot
Version: 0.8.4
Summary: aitelegrambot is a Telegram bot that uses the Ollama backend to run the LLM rationalAI (by default).
Author-email: tusharhero <tusharhero@sdf.org>, alokosx <alokosx@gmail.com>
License-File: LICENSE.md
Classifier: License :: OSI Approved :: GNU General Public License v3 or later (GPLv3+)
Classifier: Programming Language :: Python :: 3 :: Only
Requires-Dist: ollama
Requires-Dist: python-dotenv
Requires-Dist: python-telegram-bot
